{
    "login-list":
    {
        "selectorData": "login-list",
        "strategy": "css",
        "groups": [
            "requiredForPage",
            "doNotCache"
        ]
    },

    "login-count":
    {
        "selectorData": "count",
        "strategy": "class",
        "shadowParent": "login-list",
        "groups": [
            "doNotCache"]
    },

    "create-login-button":
    {
        "selectorData": "create-login-button",
        "strategy": "css",
        "shadowParent": "login-list",
        "groups": [
            "requiredForPage",
            "doNotCache"
        ]
    },

    "login-filter":
    {
        "selectorData": "login-filter",
        "strategy": "css",
        "shadowParent": "login-list",
        "groups": [
            "requiredForPage"
        ]
    },

    "login-filter-input":
    {
        "selectorData": "filter",
        "strategy": "class",
        "shadowParent": "login-filter",
        "groups": [
            "doNotCache"
        ]
    },

    "login-item":
    {
        "selectorData": "login-item",
        "strategy": "css",
        "groups": []
    },

    "login-item-type":
    {
        "selectorData": "{name}",
        "strategy": "name",
        "shadowParent": "login-item",
        "groups": []
    },

    "form-actions-row":
    {
        "selectorData": "form-actions-row",
        "strategy": "class",
        "groups": []
    },

    "save-changes-button":
    {
        "selectorData": "save-changes-button",
        "strategy": "class",
        "shadowParent": "form-actions-row",
        "groups": []
    },

    "website-address": {
        "selectorData": ".origin-input",
        "strategy": "css",
        "shadowParent": "login-item",
        "groups": []
    },

    "about-logins-page-username-field": {
        "selectorData": ".detail-row input[name='username']",
        "strategy": "css",
        "shadowParent": "login-item",
        "groups": []
    },

    "about-logins-page-password-hidden": {
        "selectorData": ".detail-row .reveal-password-wrapper .password-display",
        "strategy": "css",
        "shadowParent": "login-item",
        "groups": []
    },

    "about-logins-page-password-revealed": {
        "selectorData": ".detail-row .reveal-password-wrapper input[name='password']",
        "strategy": "css",
        "shadowParent": "login-item",
        "groups": []
    },


    "login-sort":
    {
        "selectorData": "login-sort",
        "strategy": "id",
        "shadowParent": "login-list",
        "groups": []
    },

    "password-count":
    {
        "selectorData": "count",
        "strategy": "class",
        "shadowParent": "login-list",
        "groups": []
    },

    "login-list-item": {
        "selectorData": "list-item",
        "strategy": "class",
        "shadowParent": "login-list",
        "groups": ["doNotCache"]
    },

    "menu-button":
    {
        "selectorData": "menu-button",
        "strategy": "css",
        "groups": []
    },

    "export-passwords-button":
    {
        "selectorData": "button.menuitem-button:nth-child(3)",
        "strategy": "css",
        "shadowParent": "menu-button",
        "groups": []
    },

    "confirmation-dialog":
    {
        "selectorData": "confirmation-dialog",
        "strategy": "css",
        "groups": []
    },

    "continue-export-button":
    {
        "selectorData": ".confirm-button.primary.danger-button",
        "strategy": "css",
        "shadowParent": "confirmation-dialog",
        "groups": []
    },
  
    "remove-login-button-main-page": {
        "selectorData": "delete-button",
        "strategy": "css",
        "shadowParent": "login-item",
        "groups": []
    },

    "remove-login-confirmation-dialog": {
        "selectorData": "confirmation-dialog",
        "strategy": "css",
        "groups": []
    },

    "remove-login-button-confirmation-dialog": {
        "selectorData": "confirm-button",
        "strategy": "class",
        "shadowParent": "remove-login-confirmation-dialog",
        "groups": []
    },

    "show-password-checkbox": {
       "selectorData": "input.reveal-password-checkbox",
       "strategy": "css",
       "shadowParent": "login-item",
       "groups": []
   },

    "primary-password-prompt": {
       "selectorData": "commonDialogWindow",
       "strategy": "id",
       "groups": ["doNotCache"]
   },

    "primary-password-dialog-input-field": {
       "selectorData": "password1Textbox",
       "strategy": "id",
       "groups": []
       }
    }
